{
  "date": "2026-06-29",
  "dateLabel": "seg, 29 jun",
  "greeting": "Torcida mais maravilhosa do mundo,",
  "paragraphs": [
    "A fase de grupos é um exercício de cálculo; o mata-mata, uma prova de nervos. O Canadá inaugurou os 16-avos de final ontem mostrando exatamente isso: Stephen Eustaquio furou a resiliência da África do Sul e provou que, agora, o detalhe é o destino. Hoje, o Brasil entra nesse território de vertigem contra o Japão, em Houston. A equipe de Ancelotti ostenta uma solidez defensiva rara — apenas um gol sofrido até aqui —, mas o desafio é estrutural. Sem a profundidade de Raphinha, o Brasil precisará de paciência para não cair na armadilha tática japonesa, que se especializou em atrair o domínio adversário para punir em transições cirúrgicas. É o teste da maturidade contra a velocidade. Mais tarde, a Alemanha tenta espantar a instabilidade vista contra o Equador ao encarar o Paraguai, enquanto Países Baixos e Marrocos medem quem controla melhor o espaço: o volume ofensivo holandês ou o bloqueio compacto marroquino que costuma 'roubar' o relógio do jogo. Portugal assiste aos movimentos de camarote, respirando a invencibilidade garantida contra a Colômbia enquanto aguarda o duelo de daqui a três dias contra a Croácia. No novo mapa de 32 seleções, a sobrevivência não aceita ensaios."
  ],
  "bordao": "Segue o Baile!"
}